dwave_networkx/__init__.py
dwave_networkx/default_sampler.py
dwave_networkx/exceptions.py
dwave_networkx/package_info.py
dwave_networkx/algorithms/__init__.py
dwave_networkx/algorithms/canonicalization.py
dwave_networkx/algorithms/clique.py
dwave_networkx/algorithms/coloring.py
dwave_networkx/algorithms/cover.py
dwave_networkx/algorithms/elimination_ordering.py
dwave_networkx/algorithms/independent_set.py
dwave_networkx/algorithms/markov.py
dwave_networkx/algorithms/matching.py
dwave_networkx/algorithms/max_cut.py
dwave_networkx/algorithms/partition.py
dwave_networkx/algorithms/social.py
dwave_networkx/algorithms/tsp.py
dwave_networkx/drawing/__init__.py
dwave_networkx/drawing/chimera_layout.py
dwave_networkx/drawing/distinguishable_colors.py
dwave_networkx/drawing/pegasus_layout.py
dwave_networkx/drawing/qubit_layout.py
dwave_networkx/drawing/zephyr_layout.py
dwave_networkx/generators/__init__.py
dwave_networkx/generators/chimera.py
dwave_networkx/generators/common.py
dwave_networkx/generators/markov.py
dwave_networkx/generators/pegasus.py
dwave_networkx/generators/zephyr.py
dwave_networkx/utils/__init__.py
dwave_networkx/utils/decorators.py
dwave_networkx-0.8.15.dist-info/LICENSE.txt
dwave_networkx-0.8.15.dist-info/METADATA
dwave_networkx-0.8.15.dist-info/WHEEL
dwave_networkx-0.8.15.dist-info/top_level.txt
dwave_networkx-0.8.15.dist-info/RECORD
