Metadata-Version: 2.1
Name: dwave_networkx
Version: 0.8.15
Summary: A NetworkX extension providing graphs and algorithms relevent to working with the D-Wave System
Home-page: https://github.com/dwavesystems/dwave_networkx
Download-URL: https://github.com/dwavesystems/dwave_networkx/releases
Author: D-Wave Systems Inc.
Author-email: acondello@dwavesys.com
License: Apache 2.0
Classifier: License :: OSI Approved :: Apache Software License
Classifier: Operating System :: OS Independent
Classifier: Programming Language :: Python :: 3 :: Only
Classifier: Programming Language :: Python :: 3.8
Classifier: Programming Language :: Python :: 3.9
Classifier: Programming Language :: Python :: 3.10
Classifier: Programming Language :: Python :: 3.11
Classifier: Programming Language :: Python :: 3.12
Requires-Python: >=3.8
License-File: LICENSE.txt
Requires-Dist: networkx>=2.4
Requires-Dist: dimod>=0.10.8
Requires-Dist: numpy>=1.17.3
